{
  "_id": "k4878M24UXf2PFcp",
  "name": "Speaker of Many Worlds (Sp)",
  "type": "feat",
  "_stats": {
    "coreVersion": 13,
    "systemId": "sfrpg",
    "systemVersion": "0.28.1"
  },
  "img": "systems/sfrpg/icons/default/achievement.svg",
  "system": {
    "type": "",
    "ability": null,
    "abilityMods": {
      "parts": []
    },
    "actionTarget": "",
    "actionType": "",
    "activation": {
      "type": "full",
      "condition": "",
      "cost": 0
    },
    "area": {
      "effect": "",
      "shapable": false,
      "shape": "",
      "units": "ft",
      "value": ""
    },
    "attackBonus": 0,
    "chatFlavor": "",
    "critical": {
      "effect": "",
      "parts": []
    },
    "damage": {
      "parts": []
    },
    "damageNotes": "",
    "description": {
      "chat": "",
      "gmnotes": "",
      "short": "",
      "unidentified": "",
      "value": "<p>&gt;@UUID[Compendium.sfrpg.archetypes.xrs17KSKn6uMIvCN]{Mediator}</p>\n<p>You can draw upon all known languages to make yourself understood in almost any situation. You gain the ability to cast @UUID[Compendium.sfrpg.spells.Item.uWKhr01bnKxuNRkL]{tongues} once per day as a spell-like ability. In addition, once per day as a full action, you can touch up to two willing creatures with an Intelligence modifier of at least –3 and grant them the ability to communicate with you and each other as though under the effect of tongues. This effect lasts for 1 hour or until you end it with a swift action. This is a mind-affecting affect.</p>"
    },
    "descriptors": {
      "acid": false,
      "air": false,
      "calling": false,
      "chaotic": false,
      "charm": false,
      "cold": false,
      "compulsion": false,
      "creation": false,
      "curse": false,
      "darkness": false,
      "death": false,
      "disease": false,
      "earth": false,
      "electricity": false,
      "emotion": false,
      "evil": false,
      "fear": false,
      "fire": false,
      "force": false,
      "good": false,
      "healing": false,
      "language-dependent": false,
      "lawful": false,
      "light": false,
      "mind-affecting": true,
      "pain": false,
      "poison": false,
      "polymorph": false,
      "radiation": false,
      "scrying": false,
      "sense-dependent": false,
      "shadow": false,
      "sonic": false,
      "summoning": false,
      "teleportation": false,
      "water": false
    },
    "details": {
      "category": "archetypeFeature",
      "combat": false,
      "specialAbilityType": "sp"
    },
    "duration": {
      "units": "text",
      "value": "1 hour or until you end it with a swift action"
    },
    "formula": "",
    "isActive": null,
    "modifiers": [],
    "properties": {},
    "range": {
      "additional": "",
      "per": "",
      "units": "touch",
      "value": null
    },
    "recharge": {
      "charged": false,
      "value": null
    },
    "requirements": "9th Level - Mediator",
    "rollNotes": "",
    "save": {
      "type": "",
      "dc": null,
      "descriptor": ""
    },
    "source": "NS pg. 147",
    "target": {
      "type": "",
      "value": "Two willing creatures"
    },
    "uses": {
      "max": "",
      "per": "",
      "value": null
    }
  }
}