{
  "name": "Lashunta Magic Graft",
  "type": "augmentation",
  "data": {
    "description": {
      "value": "<p>Most lashuntas have the ability to cast minor spells, even if they haven’t formally studied spellcasting. With tiny attuned crystals or magically aligned plates in your palms, you can cast <a class=\"entity-link\" draggable=\"true\" data-pack=\"sfrpg.spells\" data-id=\"cmD9XPyg0Cud1xYO\"><i class=\"fas fa-suitcase\"></i> Daze</a> and <a class=\"entity-link\" draggable=\"true\" data-pack=\"sfrpg.spells\" data-id=\"byAI5MUa3DgiiXc9\"><i class=\"fas fa-suitcase\"></i> Psychokinetic Hand</a> at will and <a class=\"entity-link\" draggable=\"true\" data-pack=\"sfrpg.spells\" data-id=\"moyeAHT4yzZVWmmg\"><i class=\"fas fa-suitcase\"></i> Detect Thoughts</a> once per day as spell-like abilities. The caster level for these effects is equal to your level.</p>",
      "chat": "",
      "unidentified": ""
    },
    "source": "AA4 pg. 145",
    "type": "biotech",
    "quantity": 1,
    "bulk": "-",
    "price": 3200,
    "level": 5,
    "attuned": false,
    "equipped": false,
    "identified": true,
    "attributes": {
      "sturdy": false,
      "customBuilt": false,
      "size": "medium",
      "dex": {
        "mod": ""
      },
      "hp": {
        "value": 10,
        "max": "10"
      },
      "hardness": {
        "value": "10"
      },
      "ac": {
        "value": "5"
      }
    },
    "modifiers": [],
    "system": "allHands",
    "damage": {
      "parts": []
    },
    "critical": {
      "parts": []
    },
    "abilityMods": {
      "parts": []
    }
  },
  "flags": {},
  "img": "systems/sfrpg/icons/classes/healing_touch.webp",
  "effects": [],
  "_id": "YvXYir0JAVQEuhZa"
}