{
  "_id": "0LaQe58OCQfHpRBp",
  "name": "Swimming fins",
  "type": "augmentation",
  "data": {
    "type": "biotech",
    "abilityMods": {
      "parts": []
    },
    "attributes": {
      "ac": {
        "value": ""
      },
      "customBuilt": false,
      "dex": {
        "mod": ""
      },
      "hardness": {
        "value": ""
      },
      "hp": {
        "max": "",
        "value": 6
      },
      "size": "medium",
      "sturdy": false
    },
    "attuned": false,
    "bulk": "-",
    "critical": {
      "parts": []
    },
    "damage": {
      "parts": []
    },
    "description": {
      "chat": "",
      "gmnotes": "",
      "short": "",
      "unidentified": "",
      "value": "<p>Your feet are altered to include broad fins, providing you with a swim speed of 20 feet. You don&rsquo;t need to attempt an Athletics check to swim. You don&rsquo;t benefit from swimming fins unless you&rsquo;re barefoot or wearing custom clothing, and you can&rsquo;t be wearing armor heavier than light armor. Swimming fins integrate into your natural feet and don&rsquo;t interfere with your normal land speed. Swimming fins can be installed into the feet of prosthetic legs.</p>"
    },
    "equippable": false,
    "equipped": false,
    "identified": true,
    "level": 2,
    "modifiers": [],
    "price": 850,
    "quantity": 1,
    "source": "ARM, p. 87",
    "system": "allFeet"
  },
  "effects": [],
  "flags": {},
  "img": "icons/svg/mystery-man.svg",
  "permission": {
    "default": 0,
    "xW89szGpnlIv5gCs": 3
  }
}