{
  "_id": "A4j6Vi3iuJeViWww",
  "name": "Electromagnetic Deflection (Ex)",
  "type": "feat",
  "img": "systems/sfrpg/icons/classes/energy_shield.webp",
  "system": {
    "type": "",
    "ability": null,
    "abilityMods": {
      "parts": []
    },
    "actionType": "",
    "activation": {
      "type": "",
      "condition": "",
      "cost": 0
    },
    "area": {
      "effect": "",
      "shape": "",
      "units": "",
      "value": 0
    },
    "attackBonus": 0,
    "chatFlavor": "",
    "critical": {
      "effect": "",
      "parts": []
    },
    "damage": {
      "parts": []
    },
    "description": {
      "chat": "",
      "unidentified": "",
      "value": "<p>&gt;@UUID[Compendium.sfrpg.class-features.YMGOKoZtKgJqIsAD]{Mechanic Trick}</p>\n<p>When you activate your energy shield, choose two of the following damage types: cold, electricity, or fire. While your shield is active, you gain resistance to the chosen damage types equal to half your mechanic level. You must have the @UUID[Compendium.sfrpg.class-features.xcIBsW8VL3DD9rVU]{Energy Shield (Ex)} mechanic trick to learn this trick.</p>"
    },
    "descriptors": [],
    "details": {
      "category": "classFeature",
      "specialAbilityType": "ex"
    },
    "duration": {
      "units": "",
      "value": null
    },
    "formula": "",
    "isActive": null,
    "modifiers": [],
    "range": {
      "additional": "",
      "per": "",
      "units": "",
      "value": null
    },
    "recharge": {
      "charged": false,
      "value": null
    },
    "requirements": "Energy Shield",
    "save": {
      "type": "",
      "dc": null,
      "descriptor": ""
    },
    "source": "AA4 pg. 61",
    "target": {
      "type": "",
      "value": null
    },
    "uses": {
      "max": 0,
      "per": null,
      "value": 0
    }
  }
}