{
  "_id": "zYajE8DDFbnd2WqV",
  "name": "Hidden Agenda (Ex)",
  "type": "feat",
  "img": "systems/sfrpg/icons/classes/hidden_agenda.webp",
  "system": {
    "type": "",
    "ability": null,
    "abilityMods": {
      "parts": []
    },
    "actionType": "",
    "activation": {
      "type": "",
      "condition": "",
      "cost": null
    },
    "area": {
      "effect": "",
      "shape": "",
      "units": null,
      "value": null
    },
    "attackBonus": 0,
    "chatFlavor": "",
    "critical": {
      "effect": "",
      "parts": []
    },
    "damage": {
      "parts": []
    },
    "description": {
      "chat": "",
      "unidentified": "",
      "value": "<p>&gt;@UUID[Compendium.sfrpg.class-features.hIhgdXnqGHBm0A64]{Envoy Improvisation}</p>\n<p>You’re an expert at veiling your true thoughts and goals. Whenever a creature attempts a Sense Motive check to detect a deception of yours, the creature must roll twice and take the worse of the two results. When you attempt a saving throw against an effect or ability that would read your thoughts or reveal your motives, you can roll twice and take the better of the two results.</p>"
    },
    "descriptors": [],
    "duration": {
      "units": "",
      "value": ""
    },
    "formula": "",
    "modifiers": [],
    "range": {
      "additional": "",
      "per": "",
      "units": null,
      "value": null
    },
    "recharge": {
      "charged": false,
      "value": null
    },
    "requirements": "8th Level",
    "save": {
      "type": "",
      "dc": null,
      "descriptor": ""
    },
    "source": "Improvisation",
    "target": {
      "type": "",
      "value": ""
    },
    "uses": {
      "max": 0,
      "per": "",
      "value": 0
    }
  }
}