{
  "name": "Microscopic Bombardment (Ex)",
  "type": "feat",
  "img": "icons/svg/mystery-man.svg",
  "data": {
    "description": {
      "chat": "",
      "gmnotes": "",
      "short": "",
      "value": "<p>&gt;@Compendium[sfrpg.class-features.fdBGqxDLdBa3mMza]{Obliteration}</p>\n<p>Your spreading swarm ability&rsquo;s secondary target can be up to 20 feet away from your initial target. In addition, you can use a nanite surge before performing a full attack to apply your spreading swarm ability to both attacks.</p>",
      "unidentified": ""
    },
    "source": "TR, p. 12",
    "type": "",
    "activation": {
      "type": "",
      "cost": 0,
      "condition": ""
    },
    "duration": {
      "value": null,
      "units": ""
    },
    "target": {
      "value": null,
      "type": ""
    },
    "area": {
      "value": 0,
      "units": "",
      "shape": "",
      "effect": ""
    },
    "range": {
      "value": null,
      "units": "",
      "additional": "",
      "per": ""
    },
    "uses": {
      "value": 0,
      "max": 0,
      "per": null
    },
    "isActive": null,
    "ability": null,
    "actionType": "",
    "attackBonus": 0,
    "chatFlavor": "",
    "critical": {
      "parts": [],
      "effect": ""
    },
    "damage": {
      "parts": []
    },
    "formula": "",
    "save": {
      "type": "",
      "dc": null,
      "descriptor": ""
    },
    "descriptors": [],
    "modifiers": [],
    "requirements": "17th Level",
    "recharge": {
      "value": null,
      "charged": false
    },
    "abilityMods": {
      "parts": []
    }
  },
  "_id": "WFyifk2f1WBbvk1X"
}